custom_switch_case/__init__.py
custom_switch_case/switchcase.py
custom_switch_case-0.0.6.dist-info/LICENSE
custom_switch_case-0.0.6.dist-info/METADATA
custom_switch_case-0.0.6.dist-info/WHEEL
custom_switch_case-0.0.6.dist-info/top_level.txt
custom_switch_case-0.0.6.dist-info/RECORD
