Metadata-Version: 2.1
Name: custom-switch-case
Version: 0.0.6
Summary: A sample python package to implement switch case in python
Author: typeyourname
Author-email: youremail@gmail.com
Classifier: Programming Language :: Python :: 3
Classifier: License :: OSI Approved :: MIT License
Classifier: Operating System :: OS Independent
Requires-Python: >=3.7
License-File: LICENSE
